mplfooty/__init__.py
mplfooty/dimensions.py
mplfooty/pitch.py
mplfooty/pitch_base.py
mplfooty/pitch_plot.py
mplfooty-0.2.0.dist-info/LICENSE
mplfooty-0.2.0.dist-info/METADATA
mplfooty-0.2.0.dist-info/WHEEL
mplfooty-0.2.0.dist-info/top_level.txt
mplfooty-0.2.0.dist-info/RECORD
